fsconnect/__init__.py
fsconnect/api.py
fsconnect/app.py
fsconnect-0.2.1.dist-info/LICENSE
fsconnect-0.2.1.dist-info/WHEEL
fsconnect-0.2.1.dist-info/METADATA
fsconnect-0.2.1.dist-info/RECORD
